sppcls/__init__.py
sppcls/event_data.py
sppcls/sppcls.py
sppcls/check/__init__.py
sppcls/check/check.py
sppcls/cli/__init__.py
sppcls/cli/sppclscli.py
sppcls/tokenise/__init__.py
sppcls/tokenise/tokenise.py
sppcls-0.1.0.dist-info/LICENSE
sppcls-0.1.0.dist-info/METADATA
sppcls-0.1.0.dist-info/WHEEL
sppcls-0.1.0.dist-info/entry_points.txt
sppcls-0.1.0.dist-info/top_level.txt
sppcls-0.1.0.dist-info/RECORD
