Metadata-Version: 2.1
Name: sppcls
Version: 0.1.0
Summary: Accessing and processing data from the DFG-funded SPP Computational Literary Studies
Author-email: Robert Jäschke <jaeschke@L3S.de>, Frederik Anrold <frederik.arnold@hu-berlin.de>
License: MIT License
Project-URL: Homepage, https://scm.cms.hu-berlin.de/schluesselstellen/spp-cls-dataexchange/code
Classifier: Programming Language :: Python :: 3
Classifier: License :: OSI Approved :: MIT License
Classifier: Operating System :: OS Independent
Requires-Python: >=3.10
License-File: LICENSE
Requires-Dist: pandas>=1.1.5
Provides-Extra: tokenise
Requires-Dist: spacy>=2.8.0; extra == "tokenise"
